Workbook

Sheet ROI Calculator
A1: Evidence Room — AP Agent Business Case Calculator
A2: Illustrative model. Not a guarantee of savings. External benchmarks: Ardent Partners 2025.
A4: Input | B4: Value | C4: Unit | D4: Notes
A5: Monthly invoice volume | B5: 15000 | C5: invoices | D5: Organisation-specific
A6: AP FTE headcount | B6: 12 | C6: FTE | D6: AP processing + exceptions
A7: Fully loaded cost per FTE (annual) | B7: 85000 | C7: USD | D7: Salary + benefits + overhead
A8: Manual-touch percentage | B8: 0.55 | C8: % | D8: Share requiring human touch
A9: Exception rate | B9: 0.184 | C9: % | D9: Default = Ardent 2025 average 18.4%
A10: Avg exception resolution minutes | B10: 18 | C10: minutes | D10: Organisation-specific
A11: Duplicate invoice rate | B11: 0.008 | C11: % | D11: Detected duplicates / invoices
A12: Late-payment cost per month | B12: 4500 | C12: USD | D12: Fees, lost discounts, cash drag
A13: Early-payment discount opportunity / mo | B13: 3200 | C13: USD | D13: Recoverable if cycle improves
A14: Current processing cost / invoice | B14: 9.84 | C14: USD | D14: Default = Ardent 2025 average
A15: AI / tooling cost per month | B15: 2500 | C15: USD | D15: LLM + orchestration + monitoring
A16: Implementation cost (one-time) | B16: 45000 | C16: USD | D16: Internal + external
... A21: External BIC cost benchmark | B21: 2.65 | C21: USD | D21: Ardent Partners 2025 Best-in-Class
A24: Scenario Outputs
A25: Metric | B25: Conservative | C25: Base | D25: Upside | E25: Formula / definition
A26: Baseline annual AP labour cost | B26: =B6*B7 | C26: =B6*B7 | D26: =B6*B7 | E26: FTE × fully loaded cost
A27: Baseline annual processing cost (volume × CPI) | B27: =B5*12*B14 | C27: =B5*12*B14 | D27: =B5*12*B14 | E27: Monthly volume × 12 × cost/invoice
A28: Estimated annual hours released | B28: =B5*12*B8*B9*(B10/60)*B17 | C28: =B5*12*B8*B9*(B10/60)*B18 | D28: =B5*12*B8*B9*(B10/60)*B19 | E28: Volume × manual% × exception% × hours × efficiency
A29: Labour capacity value released | B29: =B26*B17 | C29: =B26*B18 | D29: =B26*B19 | E29: Baseline labour × efficiency (capacity, not cash)
A30: Exception-cost reduction (illustrative) | B30: =(B5*12*B9*(B10/60)*(B7/1800))*B17 | C30: =(B5*12*B9*(B10/60)*(B7/1800))*B18 | D30: =(B5*12*B9*(B10/60)*(B7/1800))*B19 | E30: Exception hours × hourly rate × efficiency
A31: Late-payment + discount opportunity | B31: =(B12+B13)*12*B17 | C31: =(B12+B13)*12*B18 | D31: =(B12+B13)*12*B19 | E31: Cash-related opportunity × efficiency
A32: Gross annual benefit (illustrative) | B32: =B29+B30+B31 | C32: =C29+C30+C31 | D32: =D29+D30+D31 | E32: Capacity + exception + cash opportunity
A33: Annual AI / tool cost | B33: =B15*12 | C33: =B15*12 | D33: =B15*12 | E33: Monthly AI cost × 12
A34: Net annual benefit (before payback of impl) | B34: =B32-B33 | C34: =C32-C33 | D34: =D32-D33 | E34: Gross − AI cost
A35: Simple payback (months) | B35: =IF(B34<=0,"N/A",B16/(B34/12)) | C35: =IF(C34<=0,"N/A",B16/(C34/12)) | D35: =IF(D34<=0,"N/A",B16/(D34/12)) | E35: Implementation / (net monthly benefit)
A36: Year-1 ROI (illustrative) | B36: =IF((B16+B33)=0,"N/A",(B34-B16)/(B16+B33)) | C36: =IF((B16+C33)=0,"N/A",(C34-B16)/(B16+C33)) | D36: =IF((B16+D33)=0,"N/A",(D34-B16)/(B16+D33)) | E36: (Net Y1 − impl) / (impl + AI Y1)
A37: Gap to BIC cost benchmark (per invoice) | B37: =B14-B21 | C37: =B14-B21 | D37: =B14-B21 | E37: Your CPI − Ardent BIC $2.65 (context only)
A40: DISCLAIMER
A41: Illustrative planning model only. Does not guarantee savings, ROI, fraud prevention, regulatory compliance, accounting accuracy, or autonomous payment safety. Validate all inputs with your finance leaders. External benchmarks are industry research context, not targets.

Sheet Sensitivity
A1: Sensitivity — efficiency vs AI cost
A2: Illustrative heat map inputs
A4: Efficiency \ Monthly AI $ | B4: 1000 | C4: 2500 | D4: 5000 | E4: 10000
A5: 0.1 | B5: =('ROI Calculator'!B6*'ROI Calculator'!B7*0.1)-(1000*12) | C5: =('ROI Calculator'!B6*'ROI Calculator'!B7*0.1)-(2500*12) | D5: =('ROI Calculator'!B6*'ROI Calculator'!B7*0.1)-(5000*12) | E5: =('ROI Calculator'!B6*'ROI Calculator'!B7*0.1)-(10000*12)
A6: 0.15 | B6: =('ROI Calculator'!B6*'ROI Calculator'!B7*0.15)-(1000*12) | C6: =('ROI Calculator'!B6*'ROI Calculator'!B7*0.15)-(2500*12) | D6: =('ROI Calculator'!B6*'ROI Calculator'!B7*0.15)-(5000*12) | E6: =('ROI Calculator'!B6*'ROI Calculator'!B7*0.15)-(10000*12)
A7: 0.22 | B7: =('ROI Calculator'!B6*'ROI Calculator'!B7*0.22)-(1000*12) | C7: =('ROI Calculator'!B6*'ROI Calculator'!B7*0.22)-(2500*12) | D7: =('ROI Calculator'!B6*'ROI Calculator'!B7*0.22)-(5000*12) | E7: =('ROI Calculator'!B6*'ROI Calculator'!B7*0.22)-(10000*12)
A8: 0.3 | B8: =('ROI Calculator'!B6*'ROI Calculator'!B7*0.3)-(1000*12) | C8: =('ROI Calculator'!B6*'ROI Calculator'!B7*0.3)-(2500*12) | D8: =('ROI Calculator'!B6*'ROI Calculator'!B7*0.3)-(5000*12) | E8: =('ROI Calculator'!B6*'ROI Calculator'!B7*0.3)-(10000*12)
A9: 0.35 | B9: =('ROI Calculator'!B6*'ROI Calculator'!B7*0.35)-(1000*12) | C9: =('ROI Calculator'!B6*'ROI Calculator'!B7*0.35)-(2500*12) | D9: =('ROI Calculator'!B6*'ROI Calculator'!B7*0.35)-(5000*12) | E9: =('ROI Calculator'!B6*'ROI Calculator'!B7*0.35)-(10000*12)

Sheet Assumptions & Sources
A1: Assumptions & Sources
A4: Item | B4: Value | C4: Classification
A5: Ardent Partners 2025 avg cost/invoice | B5: $9.84 | C5: Independent research (Bottomline distribution)
A6: Ardent Partners 2025 BIC cost/invoice | B6: $2.65 | C6: Independent research
A7: Ardent Partners 2025 exception rate | B7: 18.4% | C7: Independent research
A8: Ardent Partners 2025 STP | B8: 35.4% | C8: Independent research
A9: Organisation inputs | B9: Editable | C9: Replace defaults with your actuals
A10: Efficiency gains | B10: Illustrative ranges | C10: Not promises — calibrate in shadow/pilot
