Workbook

Sheet Inputs
A1: Evidence Room · AP Agent Business Case
A2: Customer baseline only. Scenarios are model outputs, not promises. Version 1.0 · Sep 2026
A4: Parameter | B4: Unit | C4: Conservative | D4: Base | E4: Upside | F4: Notes
A5: Monthly invoice volume | B5: invoices | C5: 15000 | D5: 18000 | E5: 22000 | F5: Northline illustrative default in Base
A6: AP FTE (payables processing) | B6: FTE | C6: 14 | D6: 14 | E6: 12 | F6: Shared-services headcount touching invoices
A7: Fully loaded cost per FTE | B7: USD / year | C7: 85000 | D7: 95000 | E7: 105000 | F7: Salary + burden; customer actuals
A8: Manual-touch rate | B8: % invoices | C8: 0.72 | D8: 0.62 | E8: 0.48 | F8: Share requiring a human touch today
A9: Exception rate | B9: % invoices | C9: 0.24 | D9: 0.2 | E9: 0.14 | F9: Ardent 2024 BIC reported 9%; do not import as your target
A10: Avg resolution minutes | B10: minutes | C10: 28 | D10: 22 | E10: 16 | F10: Clock time per exception, not elapsed days
A11: Known duplicate rate | B11: % invoices | C11: 0.004 | D11: 0.003 | E11: 0.002 | F11: Confirmed duplicates; not a fraud rate
A12: Avg invoice value (for sensitivity only) | B12: USD | C12: 1800 | D12: 2200 | E12: 2600 | F12: Used only if you model cash leakage
A13: Late-payment cost / month | B13: USD | C13: 8000 | D13: 5000 | E13: 2000 | F13: Fees + lost discount + supplier friction estimate
A14: Early-pay discount opportunity / month | B14: USD | C14: 4000 | D14: 7000 | E14: 12000 | F14: Uncaptured discounts — customer AP data
A15: Current processing cost / invoice | B15: USD | C15: 12.5 | D15: 9.8 | E15: 7.4 | F15: YOUR cost. Do not paste vendor-blog $15/$3
A16: AI / tool run-rate / month | B16: USD | C16: 4500 | D16: 6500 | E16: 9000 | F16: Models + orchestration + licences
... A22: Model years | B22: years | C22: 3 | D22: 3 | E22: 3 | F22: Horizon for ROI/payback
A24: ILLUSTRATIVE model. Evidence Room does not promise savings, ROI, payback, or discount capture. Replace every yellow-adjacent input with the customer's measured baseline. Absolute $ cost-per-invoice figures circulating in vendor blogs ($10–$15 vs $2–$3) are not independent facts. Ardent Partners 2024 Best-in-Class reported 78% lower cost, 82% faster cycle, 59% lower exceptions vs peers, and a 9% BIC exception rate — context, not a forecast.

Sheet Model
A1: Calculated outcomes
A2: Formulas read Inputs! Conservative / Base / Upside. Hours are not cash until Hours-to-cash conversion.
A4: Metric | B4: Conservative | C4: Base | D4: Upside
A5: Annual invoices | B5: =Inputs!C5*12 | C5: =Inputs!D5*12 | D5: =Inputs!E5*12
A6: Annual labour cost | B6: =Inputs!C6*Inputs!C7 | C6: =Inputs!D6*Inputs!D7 | D6: =Inputs!E6*Inputs!E7
A7: Baseline processing cost / year | B7: =B5*Inputs!C15 | C7: =C5*Inputs!D15 | D7: =D5*Inputs!E15
A8: Manual-touch invoices / year | B8: =B5*Inputs!C8 | C8: =C5*Inputs!D8 | D8: =D5*Inputs!E8
A9: Exceptions / year | B9: =B5*Inputs!C9 | C9: =C5*Inputs!D9 | D9: =D5*Inputs!E9
A10: Exception hours / year | B10: =B9*Inputs!C10/60 | C10: =C9*Inputs!D10/60 | D10: =D9*Inputs!E10/60
A11: Gross hours released / year | B11: =B10*Inputs!C18 + (B8*0.08*Inputs!C18) | C11: =C10*Inputs!D18 + (C8*0.08*Inputs!D18) | D11: =D10*Inputs!E18 + (D8*0.08*Inputs!E18)
A12: Cash-converted labour / year | B12: =B11*(Inputs!C7/1800)*Inputs!C20 | C12: =C11*(Inputs!D7/1800)*Inputs!D20 | D12: =D11*(Inputs!E7/1800)*Inputs!E20
A13: Processing cost change / year | B13: =B7*Inputs!C18 | C13: =C7*Inputs!D18 | D13: =D7*Inputs!E18
A14: Exception cost change / year | B14: =B10*(Inputs!C7/1800)*Inputs!C19 | C14: =C10*(Inputs!D7/1800)*Inputs!D19 | D14: =D10*(Inputs!E7/1800)*Inputs!E19
A15: Late-cost reduction / year | B15: =Inputs!C13*12*Inputs!C18 | C15: =Inputs!D13*12*Inputs!D18 | D15: =Inputs!E13*12*Inputs!E18
A16: Discount capture / year | B16: =Inputs!C14*12*Inputs!C21 | C16: =Inputs!D14*12*Inputs!D21 | D16: =Inputs!E14*12*Inputs!E21
A17: AI + tool cost / year | B17: =Inputs!C16*12 | C17: =Inputs!D16*12 | D17: =Inputs!E16*12
A18: Gross annual benefit (pre-tool) | B18: =B12+B13+B14+B15+B16 | C18: =C12+C13+C14+C15+C16 | D18: =D12+D13+D14+D15+D16
A19: Net annual benefit | B19: =B18-B17 | C19: =C18-C17 | D19: =D18-D17
A20: Implementation cost | B20: =Inputs!C17 | C20: =Inputs!D17 | D20: =Inputs!E17
A21: Payback (months) | B21: =IF(B19<=0,"No payback in model",B20/(B19/12)) | C21: =IF(C19<=0,"No payback in model",C20/(C19/12)) | D21: =IF(D19<=0,"No payback in model",D20/(D19/12))
A22: 3-year net (undiscounted) | B22: =B19*Inputs!C22-B20 | C22: =C19*Inputs!D22-C20 | D22: =D19*Inputs!E22-D20
A23: ROI (3-year, undiscounted) | B23: =IF(B20=0,"n/a",B22/B20) | C23: =IF(C20=0,"n/a",C22/C20) | D23: =IF(D20=0,"n/a",D22/D20)
A26: If Net annual benefit is negative, say so. Do not force a payback story. Conservative is the steering case until measured results exist.
A28: Scenario | B28: Net annual benefit
A29: Conservative | B29: =B19
A30: Base | B30: =C19
A31: Upside | B31: =D19

Sheet How to use
A1: How to brief a CFO with this model
A2: Four families: do not present financials without operational and control evidence.
A4: 1. Replace Inputs with a measured month (volume, FTE, loaded cost, exception rate, minutes). 2. Leave scenario spreads wide. False precision is a credibility failure. 3. Hours released ≠ savings. Apply Hours-to-cash conversion or report capacity only. 4. Put control breaches and rework next to any efficiency claim (see KPI workbook). 5. Payment authorisation remains human. Do not model 'straight-through pay' as a default. 6. Cite Ardent 2024 only as industry context, never as 'you will achieve'. 7. If Base does not pay back, the honest answer is: do not scale spend; run one bounded agent.
