Workbook

Sheet Assumptions
A1: Evidence Room — AP Agent OS
A2: ER Business Case Model
A3: Board-ready structure — illustrative until you own the inputs
A4: Agents that earn responsibility.
A6: ID | B6: Assumption | C6: Value | D6: Unit / note
A7: A1 | B7: Annual invoice volume | C7: 120000 | D7: invoices
A8: A2 | B8: Current cost per invoice | C8: 12.5 | D8: USD
A9: A3 | B9: Target cost per invoice (internal goal) | C9: 10 | D9: USD — internal goal, not industry promise
A10: A4 | B10: AP loaded labour pool | C10: 680000 | D10: USD/year
A11: A5 | B11: One-time implementation | C11: 75000 | D11: USD
A12: A6 | B12: Annual platform / AI run cost | C12: 48000 | D12: USD
A13: A7 | B13: Change / training cost (Y1) | C13: 25000 | D13: USD
A14: A8 | B14: Benefit realisation ramp Y1 | C14: 0.5 | D14: fraction
A15: A9 | B15: Benefit realisation ramp Y2 | C15: 0.85 | D15: fraction
A16: A10 | B16: Benefit realisation ramp Y3 | C16: 1 | D16: fraction
A17: A11 | B17: Working capital benefit (annual, optional) | C17: 40000 | D17: USD — optional
A18: A12 | B18: Risk reduction value (qualitative $) | C18: 20000 | D18: USD — conservative proxy
... A20: A14 | B20: Horizon years | C20: 3 | D20: years

Sheet Cashflow
A1: Evidence Room — AP Agent OS
A2: 3-Year Cashflow (formulas)
A3: ILLUSTRATIVE until Assumptions are yours
A4: Agents that earn responsibility.
A6: Line | B6: Year 1 | C6: Year 2 | D6: Year 3
A7: Gross cost/invoice savings | B7: =Assumptions!C7*(Assumptions!C8-Assumptions!C9)*Assumptions!C14 | C7: =Assumptions!C7*(Assumptions!C8-Assumptions!C9)*Assumptions!C15 | D7: =Assumptions!C7*(Assumptions!C8-Assumptions!C9)*Assumptions!C16
A8: Working capital benefit | B8: =Assumptions!C17*Assumptions!C14 | C8: =Assumptions!C17*Assumptions!C15 | D8: =Assumptions!C17*Assumptions!C16
A9: Risk reduction proxy | B9: =Assumptions!C18*Assumptions!C14 | C9: =Assumptions!C18*Assumptions!C15 | D9: =Assumptions!C18*Assumptions!C16
A10: Total benefits | B10: =B7+B8+B9 | C10: =C7+C8+C9 | D10: =D7+D8+D9
A11: Platform / AI run cost | B11: =Assumptions!C12 | C11: =Assumptions!C12 | D11: =Assumptions!C12
A12: Implementation (one-time) | B12: =Assumptions!C11 | C12: 0 | D12: 0
A13: Change / training | B13: =Assumptions!C13 | C13: 0 | D13: 0
A14: Total costs | B14: =B11+B12+B13 | C14: =C11+C12+C13 | D14: =D11+D12+D13
A15: Net cashflow | B15: =B10-B14 | C15: =C10-C14 | D15: =D10-D14
A17: Cumulative | B17: =B15 | C17: =B17+C15 | D17: =C17+D15
A19: NPV (3yr) | B19: =B15/(1+Assumptions!C19)+C15/(1+Assumptions!C19)^2+D15/(1+Assumptions!C19)^3
A20: Simple ROI (3yr benefits / 3yr costs) | B20: =(B10+C10+D10)/(B14+C14+D14)
A22: ILLUSTRATIVE MODEL — industry averages are external context on Notes only, not embedded targets.

Sheet Exec Summary
A1: Evidence Room — AP Agent OS
A2: Executive Summary Fields
A3: Narrative hooks for board pack
A4: Agents that earn responsibility.
A6: Problem statement | B6: AP lacks a governed agent operating model; exceptions and evidence are uneven.
A7: Proposed approach | B7: Evidence Room earn-up: Observe → Recommend → Draft → Execute (narrow) → Expand.
A8: Investment asked | B8: Y1 implementation + change costs; ongoing platform run cost (see Assumptions).
A9: Decision requested | B9: Approve Phase 0–3 pilot with kill-switches; revisit bounded execute after earn-in.
A10: Non-goals | B10: No guaranteed cost/invoice to industry average; no unsupervised payment release; no fraud certainty claims.

Sheet Notes
A1: Evidence Room — AP Agent OS
A2: Notes & External Benchmarks
A3: Industry context only — not a guarantee of your results
A4: Agents that earn responsibility.
A6: Field | B6: Value
A7: Source | B7: Ardent Partners — State of ePayables (2025 survey averages)
A8: Avg cost per invoice | B8: $9.84
A9: Exception rate | B9: 18.4%
A10: Straight-through processing (STP) | B10: 35.4%
A11: Label | B11: EXTERNAL BENCHMARK — NOT A GUARANTEE
A12: How to use | B12: Locate your baseline relative to survey averages. Do not substitute these for measured KPIs or treat them as Evidence Room performance claims.
A13: Forbidden use | B13: Do not market 'guaranteed to reach $9.84'. Worksheets labeled ILLUSTRATIVE require your own inputs.
A14: Product | B14: Evidence Room provides methodologies and templates. Humans remain accountable for approvals, payments, and audit representations.

Sheet Disclaimer
A1: Evidence Room — AP Agent OS
A2: Disclaimer
A3: Read before relying on model outputs
A4: Agents that earn responsibility.
A6: Evidence Room products provide educational and operational templates for designing, governing, and measuring AI agents that assist Accounts Payable work.
A7: They are not legal, tax, audit, accounting, investment, or compliance advice.
A8: They are not a substitute for your ERP, AP automation platform, payment provider, or professional advisors.
A9: AI agents can be wrong. Humans remain accountable for approvals, postings, payments, supplier master changes, and representations to auditors.
A10: We do not guarantee any reduction in cost per invoice, cycle time, exception rate, fraud losses, compliance findings, or ROI.
A11: Industry benchmarks attributed to Ardent Partners (2025) — $9.84 avg cost/invoice, 18.4% exception rate, 35.4% STP — are third-party survey averages for context only. Cited only on Notes sheets.
A12: Any cell labeled ILLUSTRATIVE is sample data for structure demonstration — replace with your measured figures before decisions.
A13: Confidential — licensed for internal use by the purchasing organisation.
