Workbook

Sheet Diagnostic
A1: Evidence Room — AP Agent OS
A2: ER Maturity Diagnostic — 35 questions
A3: Score 0–4 each; maturity auto-calcs
A4: Agents that earn responsibility.
A5: Scoring: 0 Absent · 1 Ad hoc · 2 Emerging · 3 Established · 4 Managed
A6: Dimension | B6: ID | C6: Statement | D6: Score (0–4) | E6: Evidence / notes
A7: Process | B7: P1 | C7: Invoice intake channels are documented with an owner for each channel. | D7: 3 | E7: ILLUSTRATIVE sample score — replace
A8: Process | B8: P2 | C8: Written standard for invoice completeness before AP queue entry. | D8: 2 | E8: ILLUSTRATIVE sample score — replace
A9: Process | B9: P3 | C9: PO and non-PO paths separated with different handling rules. | D9: 3 | E9: ILLUSTRATIVE sample score — replace
A10: Process | B10: P4 | C10: Exception types catalogued with defined owners. | D10: 2 | E10: ILLUSTRATIVE sample score — replace
A11: Process | B11: P5 | C11: Approval matrices current and applied consistently. | D11: 3 | E11: ILLUSTRATIVE sample score — replace
A12: Process | B12: P6 | C12: Payment runs follow published calendar with cut-offs and holds. | D12: 2 | E12: ILLUSTRATIVE sample score — replace
A13: Process | B13: P7 | C13: Period-close AP tasks are checklist-driven. | D13: 2 | E13: ILLUSTRATIVE sample score — replace
A14: Data | B14: D1 | C14: Vendor master payment fields defined and enforced. | D14: 3 | E14: ILLUSTRATIVE sample score — replace
A15: Data | B15: D2 | C15: Duplicate vendor records reviewed on a schedule. | D15: 2 | E15: ILLUSTRATIVE sample score — replace
A16: Data | B16: D3 | C16: Invoice fields map cleanly to ERP without habitual free-text. | D16: 2 | E16: ILLUSTRATIVE sample score — replace
A17: Data | B17: D4 | C17: PO, GR, and invoice identifiers join reliably for matching. | D17: 3 | E17: ILLUSTRATIVE sample score — replace
A18: Data | B18: D5 | C18: ≥12 months historical invoices queryable for patterns. | D18: 2 | E18: ILLUSTRATIVE sample score — replace
... A41: Measurement | B41: M4 | C41: KPI reviews on fixed cadence with owners and actions. | D41: 2 | E41: ILLUSTRATIVE sample score — replace

Sheet Scoring Summary
A1: Evidence Room — AP Agent OS
A2: Auto Maturity Scoring
A3: Formulas over Diagnostic!D7:D41
A4: Agents that earn responsibility.
A6: Dimension | B6: Your points | C6: Max | D6: % of max | E6: Band
A7: Process | B7: =SUM(Diagnostic!D7:D13) | C7: 28 | D7: =IF(C7=0,0,B7/C7) | E7: =IF(D7<0.25,"Fragile",IF(D7<0.5,"Forming",IF(D7<0.75,"Capable",IF(D7<0.9,"Strong","Evidence-ready"))))
A8: Data | B8: =SUM(Diagnostic!D14:D19) | C8: 24 | D8: =IF(C8=0,0,B8/C8) | E8: =IF(D8<0.25,"Fragile",IF(D8<0.5,"Forming",IF(D8<0.75,"Capable",IF(D8<0.9,"Strong","Evidence-ready"))))
A9: Controls | B9: =SUM(Diagnostic!D20:D26) | C9: 28 | D9: =IF(C9=0,0,B9/C9) | E9: =IF(D9<0.25,"Fragile",IF(D9<0.5,"Forming",IF(D9<0.75,"Capable",IF(D9<0.9,"Strong","Evidence-ready"))))
A10: Technology | B10: =SUM(Diagnostic!D27:D32) | C10: 24 | D10: =IF(C10=0,0,B10/C10) | E10: =IF(D10<0.25,"Fragile",IF(D10<0.5,"Forming",IF(D10<0.75,"Capable",IF(D10<0.9,"Strong","Evidence-ready"))))
A11: People | B11: =SUM(Diagnostic!D33:D37) | C11: 20 | D11: =IF(C11=0,0,B11/C11) | E11: =IF(D11<0.25,"Fragile",IF(D11<0.5,"Forming",IF(D11<0.75,"Capable",IF(D11<0.9,"Strong","Evidence-ready"))))
A12: Measurement | B12: =SUM(Diagnostic!D38:D41) | C12: 16 | D12: =IF(C12=0,0,B12/C12) | E12: =IF(D12<0.25,"Fragile",IF(D12<0.5,"Forming",IF(D12<0.75,"Capable",IF(D12<0.9,"Strong","Evidence-ready"))))
A14: Total points | B14: =SUM(B7:B12) | C14: 140 | D14: =B14/C14
A15: Maturity level | B15: =IF(B14<=27,1,IF(B14<=55,2,IF(B14<=83,3,IF(B14<=111,4,5)))) | C15: =IF(B15=1,"Manual & opaque",IF(B15=2,"Documented but fragile",IF(B15=3,"Controlled operations",IF(B15=4,"Measurable & integrable","Agent-ready with governance"))))
A17: Sample scores on Diagnostic sheet are ILLUSTRATIVE. Overwrite with evidence-based scores.

Sheet Level Guide
A1: Evidence Room — AP Agent OS
A2: Maturity Levels 1–5
A3: Agent posture by level
A4: Agents that earn responsibility.
A6: Level | B6: Points | C6: Label | D6: Agent posture
A7: 1 | B7: 0–27 | C7: Manual & opaque | D7: Observation only
A8: 2 | B8: 28–55 | C8: Documented but fragile | D8: Draft-only, 100% human action
A9: 3 | B9: 56–83 | C9: Controlled operations | D9: Propose-and-confirm
A10: 4 | B10: 84–111 | C10: Measurable & integrable | D10: Bounded autonomy narrow classes
A11: 5 | B11: 112–140 | C11: Agent-ready with governance | D11: Portfolio with RACI & sampling

Sheet Notes
A1: Evidence Room — AP Agent OS
A2: Notes & External Benchmarks
A3: Industry context only — not a guarantee of your results
A4: Agents that earn responsibility.
A6: Field | B6: Value
A7: Source | B7: Ardent Partners — State of ePayables (2025 survey averages)
A8: Avg cost per invoice | B8: $9.84
A9: Exception rate | B9: 18.4%
A10: Straight-through processing (STP) | B10: 35.4%
A11: Label | B11: EXTERNAL BENCHMARK — NOT A GUARANTEE
A12: How to use | B12: Locate your baseline relative to survey averages. Do not substitute these for measured KPIs or treat them as Evidence Room performance claims.
A13: Forbidden use | B13: Do not market 'guaranteed to reach $9.84'. Worksheets labeled ILLUSTRATIVE require your own inputs.
A14: Product | B14: Evidence Room provides methodologies and templates. Humans remain accountable for approvals, payments, and audit representations.

Sheet Disclaimer
A1: Evidence Room — AP Agent OS
A2: Disclaimer
A3: Read before relying on model outputs
A4: Agents that earn responsibility.
A6: Evidence Room products provide educational and operational templates for designing, governing, and measuring AI agents that assist Accounts Payable work.
A7: They are not legal, tax, audit, accounting, investment, or compliance advice.
A8: They are not a substitute for your ERP, AP automation platform, payment provider, or professional advisors.
A9: AI agents can be wrong. Humans remain accountable for approvals, postings, payments, supplier master changes, and representations to auditors.
A10: We do not guarantee any reduction in cost per invoice, cycle time, exception rate, fraud losses, compliance findings, or ROI.
A11: Industry benchmarks attributed to Ardent Partners (2025) — $9.84 avg cost/invoice, 18.4% exception rate, 35.4% STP — are third-party survey averages for context only. Cited only on Notes sheets.
A12: Any cell labeled ILLUSTRATIVE is sample data for structure demonstration — replace with your measured figures before decisions.
A13: Confidential — licensed for internal use by the purchasing organisation.
