Workbook

Sheet Inputs
A1: Evidence Room — AP Agent OS
A2: ER ROI Calculator — Inputs
A3: Edit input cells (paper fill) only
A4: Agents that earn responsibility.
A6: Parameter | B6: Value | C6: Unit | D6: Notes
A7: Annual invoice volume | B7: 120000 | C7: invoices/year | D7: INPUT — editable
A8: AP headcount (FTE) | B8: 8 | C8: FTE | D8: INPUT — editable
A9: Loaded cost per FTE | B9: 85000 | C9: USD/year | D9: INPUT — editable
A10: Manual-touch share | B10: 0.65 | C10: % of invoices | D10: INPUT — editable
A11: Exception rate | B11: 0.22 | C11: % of invoices | D11: INPUT — editable
A12: Minutes per exception resolution | B12: 18 | C12: minutes | D12: INPUT — editable
A13: Duplicate payment loss rate | B13: 0.0015 | C13: fraction of spend | D13: INPUT — editable
A14: Annual AP spend (proxy) | B14: 48000000 | C14: USD | D14: INPUT — editable
A15: Late-payment cost / year | B15: 120000 | C15: USD | D15: INPUT — editable
A16: Early-pay discount opportunity | B16: 95000 | C16: USD/year missed | D16: INPUT — editable
A17: Current processing cost / invoice | B17: 12.5 | C17: USD | D17: INPUT — editable
A18: Projected AI platform cost / year | B18: 48000 | C18: USD | D18: INPUT — editable
... A27: Model years | B27: 3 | C27: years | D27: INPUT — editable
A29: Derived labour pool | B29: =B8*B9 | C29: Annual loaded AP labour
A30: Derived exception hours | B30: =B7*B11*B12/60 | C30: Hours/year on exceptions

Sheet Outputs
A1: Evidence Room — AP Agent OS
A2: Scenario Outputs
A3: Conservative / Base / Upside — formula-driven
A4: Agents that earn responsibility.
A6: Metric | B6: Conservative | C6: Base | D6: Upside
A7: Labour savings (annual) | B7: =Inputs!B29*Inputs!B20*Inputs!B23 | C7: =Inputs!B29*Inputs!B21*Inputs!B23 | D7: =Inputs!B29*Inputs!B22*Inputs!B23
A8: Exception capacity value | B8: =Inputs!B30*(Inputs!B9/2080)*Inputs!B20 | C8: =Inputs!B30*(Inputs!B9/2080)*Inputs!B21 | D8: =Inputs!B30*(Inputs!B9/2080)*Inputs!B22
A9: Late-pay reduction value | B9: =Inputs!B15*Inputs!B25*Inputs!B20/Inputs!B21 | C9: =Inputs!B15*Inputs!B25 | D9: =Inputs!B15*Inputs!B25*Inputs!B22/Inputs!B21
A10: Early-pay capture | B10: =Inputs!B16*Inputs!B24*Inputs!B20/Inputs!B21 | C10: =Inputs!B16*Inputs!B24 | D10: =Inputs!B16*Inputs!B24*Inputs!B22/Inputs!B21
A11: Duplicate loss avoided | B11: =Inputs!B14*Inputs!B13*Inputs!B26*Inputs!B20/Inputs!B21 | C11: =Inputs!B14*Inputs!B13*Inputs!B26 | D11: =Inputs!B14*Inputs!B13*Inputs!B26*Inputs!B22/Inputs!B21
A12: Gross annual benefit | B12: =B7+B8+B9+B10+B11 | C12: =C7+C8+C9+C10+C11 | D12: =D7+D8+D9+D10+D11
A13: AI + run cost | B13: =Inputs!B18 | C13: =Inputs!B18 | D13: =Inputs!B18
A14: Net annual benefit (Y2+) | B14: =B12-B13 | C14: =C12-C13 | D14: =D12-D13
A15: Year-1 net (after impl.) | B15: =B14-Inputs!B19 | C15: =C14-Inputs!B19 | D15: =D14-Inputs!B19
A16: 3-year cumulative net | B16: =B15+B14*2 | C16: =C15+C14*2 | D16: =D15+D14*2
A17: Payback months (approx) | B17: =IF(B14<=0,"n/a",Inputs!B19/(B14/12)) | C17: =IF(C14<=0,"n/a",Inputs!B19/(C14/12)) | D17: =IF(D14<=0,"n/a",Inputs!B19/(D14/12))
A18: Illustrative cost/invoice after | B18: =Inputs!B17*(1-Inputs!B20) | C18: =Inputs!B17*(1-Inputs!B21) | D18: =Inputs!B17*(1-Inputs!B22)
A20: ILLUSTRATIVE MODEL — replace Inputs with your data. Not a savings guarantee.

Sheet Sensitivity
A1: Evidence Room — AP Agent OS
A2: Sensitivity — Efficiency × Volume
A3: Base-scaled net annual benefit
A4: Agents that earn responsibility.
A6: Eff. gain \ Annual volume | B6: 60000 | C6: 90000 | D6: 120000 | E6: 180000 | F6: 240000
A7: 0.1 | B7: =Inputs!B8*Inputs!B9*0.1*Inputs!B23+(Inputs!B15*Inputs!B25+Inputs!B16*Inputs!B24+Inputs!B14*Inputs!B13*Inputs!B26)*(60000/Inputs!B7)*(0.1/Inputs!B21)-Inputs!B18 | C7: =Inputs!B8*Inputs!B9*0.1*Inputs!B23+(Inputs!B15*Inputs!B25+Inputs!B16*Inputs!B24+Inputs!B14*Inputs!B13*Inputs!B26)*(90000/Inputs!B7)*(0.1/Inputs!B21)-Inputs!B18 | D7: =Inputs!B8*Inputs!B9*0.1*Inputs!B23+(Inputs!B15*Inputs!B25+Inputs!B16*Inputs!B24+Inputs!B14*Inputs!B13*Inputs!B26)*(120000/Inputs!B7)*(0.1/Inputs!B21)-Inputs!B18 | E7: =Inputs!B8*Inputs!B9*0.1*Inputs!B23+(Inputs!B15*Inputs!B25+Inputs!B16*Inputs!B24+Inputs!B14*Inputs!B13*Inputs!B26)*(180000/Inputs!B7)*(0.1/Inputs!B21)-Inputs!B18 | F7: =Inputs!B8*Inputs!B9*0.1*Inputs!B23+(Inputs!B15*Inputs!B25+Inputs!B16*Inputs!B24+Inputs!B14*Inputs!B13*Inputs!B26)*(240000/Inputs!B7)*(0.1/Inputs!B21)-Inputs!B18
A8: 0.15 | B8: =Inputs!B8*Inputs!B9*0.15*Inputs!B23+(Inputs!B15*Inputs!B25+Inputs!B16*Inputs!B24+Inputs!B14*Inputs!B13*Inputs!B26)*(60000/Inputs!B7)*(0.15/Inputs!B21)-Inputs!B18 | C8: =Inputs!B8*Inputs!B9*0.15*Inputs!B23+(Inputs!B15*Inputs!B25+Inputs!B16*Inputs!B24+Inputs!B14*Inputs!B13*Inputs!B26)*(90000/Inputs!B7)*(0.15/Inputs!B21)-Inputs!B18 | D8: =Inputs!B8*Inputs!B9*0.15*Inputs!B23+(Inputs!B15*Inputs!B25+Inputs!B16*Inputs!B24+Inputs!B14*Inputs!B13*Inputs!B26)*(120000/Inputs!B7)*(0.15/Inputs!B21)-Inputs!B18 | E8: =Inputs!B8*Inputs!B9*0.15*Inputs!B23+(Inputs!B15*Inputs!B25+Inputs!B16*Inputs!B24+Inputs!B14*Inputs!B13*Inputs!B26)*(180000/Inputs!B7)*(0.15/Inputs!B21)-Inputs!B18 | F8: =Inputs!B8*Inputs!B9*0.15*Inputs!B23+(Inputs!B15*Inputs!B25+Inputs!B16*Inputs!B24+Inputs!B14*Inputs!B13*Inputs!B26)*(240000/Inputs!B7)*(0.15/Inputs!B21)-Inputs!B18
A9: 0.2 | B9: =Inputs!B8*Inputs!B9*0.2*Inputs!B23+(Inputs!B15*Inputs!B25+Inputs!B16*Inputs!B24+Inputs!B14*Inputs!B13*Inputs!B26)*(60000/Inputs!B7)*(0.2/Inputs!B21)-Inputs!B18 | C9: =Inputs!B8*Inputs!B9*0.2*Inputs!B23+(Inputs!B15*Inputs!B25+Inputs!B16*Inputs!B24+Inputs!B14*Inputs!B13*Inputs!B26)*(90000/Inputs!B7)*(0.2/Inputs!B21)-Inputs!B18 | D9: =Inputs!B8*Inputs!B9*0.2*Inputs!B23+(Inputs!B15*Inputs!B25+Inputs!B16*Inputs!B24+Inputs!B14*Inputs!B13*Inputs!B26)*(120000/Inputs!B7)*(0.2/Inputs!B21)-Inputs!B18 | E9: =Inputs!B8*Inputs!B9*0.2*Inputs!B23+(Inputs!B15*Inputs!B25+Inputs!B16*Inputs!B24+Inputs!B14*Inputs!B13*Inputs!B26)*(180000/Inputs!B7)*(0.2/Inputs!B21)-Inputs!B18 | F9: =Inputs!B8*Inputs!B9*0.2*Inputs!B23+(Inputs!B15*Inputs!B25+Inputs!B16*Inputs!B24+Inputs!B14*Inputs!B13*Inputs!B26)*(240000/Inputs!B7)*(0.2/Inputs!B21)-Inputs!B18
A10: 0.25 | B10: =Inputs!B8*Inputs!B9*0.25*Inputs!B23+(Inputs!B15*Inputs!B25+Inputs!B16*Inputs!B24+Inputs!B14*Inputs!B13*Inputs!B26)*(60000/Inputs!B7)*(0.25/Inputs!B21)-Inputs!B18 | C10: =Inputs!B8*Inputs!B9*0.25*Inputs!B23+(Inputs!B15*Inputs!B25+Inputs!B16*Inputs!B24+Inputs!B14*Inputs!B13*Inputs!B26)*(90000/Inputs!B7)*(0.25/Inputs!B21)-Inputs!B18 | D10: =Inputs!B8*Inputs!B9*0.25*Inputs!B23+(Inputs!B15*Inputs!B25+Inputs!B16*Inputs!B24+Inputs!B14*Inputs!B13*Inputs!B26)*(120000/Inputs!B7)*(0.25/Inputs!B21)-Inputs!B18 | E10: =Inputs!B8*Inputs!B9*0.25*Inputs!B23+(Inputs!B15*Inputs!B25+Inputs!B16*Inputs!B24+Inputs!B14*Inputs!B13*Inputs!B26)*(180000/Inputs!B7)*(0.25/Inputs!B21)-Inputs!B18 | F10: =Inputs!B8*Inputs!B9*0.25*Inputs!B23+(Inputs!B15*Inputs!B25+Inputs!B16*Inputs!B24+Inputs!B14*Inputs!B13*Inputs!B26)*(240000/Inputs!B7)*(0.25/Inputs!B21)-Inputs!B18
A11: 0.3 | B11: =Inputs!B8*Inputs!B9*0.3*Inputs!B23+(Inputs!B15*Inputs!B25+Inputs!B16*Inputs!B24+Inputs!B14*Inputs!B13*Inputs!B26)*(60000/Inputs!B7)*(0.3/Inputs!B21)-Inputs!B18 | C11: =Inputs!B8*Inputs!B9*0.3*Inputs!B23+(Inputs!B15*Inputs!B25+Inputs!B16*Inputs!B24+Inputs!B14*Inputs!B13*Inputs!B26)*(90000/Inputs!B7)*(0.3/Inputs!B21)-Inputs!B18 | D11: =Inputs!B8*Inputs!B9*0.3*Inputs!B23+(Inputs!B15*Inputs!B25+Inputs!B16*Inputs!B24+Inputs!B14*Inputs!B13*Inputs!B26)*(120000/Inputs!B7)*(0.3/Inputs!B21)-Inputs!B18 | E11: =Inputs!B8*Inputs!B9*0.3*Inputs!B23+(Inputs!B15*Inputs!B25+Inputs!B16*Inputs!B24+Inputs!B14*Inputs!B13*Inputs!B26)*(180000/Inputs!B7)*(0.3/Inputs!B21)-Inputs!B18 | F11: =Inputs!B8*Inputs!B9*0.3*Inputs!B23+(Inputs!B15*Inputs!B25+Inputs!B16*Inputs!B24+Inputs!B14*Inputs!B13*Inputs!B26)*(240000/Inputs!B7)*(0.3/Inputs!B21)-Inputs!B18
A12: 0.35 | B12: =Inputs!B8*Inputs!B9*0.35*Inputs!B23+(Inputs!B15*Inputs!B25+Inputs!B16*Inputs!B24+Inputs!B14*Inputs!B13*Inputs!B26)*(60000/Inputs!B7)*(0.35/Inputs!B21)-Inputs!B18 | C12: =Inputs!B8*Inputs!B9*0.35*Inputs!B23+(Inputs!B15*Inputs!B25+Inputs!B16*Inputs!B24+Inputs!B14*Inputs!B13*Inputs!B26)*(90000/Inputs!B7)*(0.35/Inputs!B21)-Inputs!B18 | D12: =Inputs!B8*Inputs!B9*0.35*Inputs!B23+(Inputs!B15*Inputs!B25+Inputs!B16*Inputs!B24+Inputs!B14*Inputs!B13*Inputs!B26)*(120000/Inputs!B7)*(0.35/Inputs!B21)-Inputs!B18 | E12: =Inputs!B8*Inputs!B9*0.35*Inputs!B23+(Inputs!B15*Inputs!B25+Inputs!B16*Inputs!B24+Inputs!B14*Inputs!B13*Inputs!B26)*(180000/Inputs!B7)*(0.35/Inputs!B21)-Inputs!B18 | F12: =Inputs!B8*Inputs!B9*0.35*Inputs!B23+(Inputs!B15*Inputs!B25+Inputs!B16*Inputs!B24+Inputs!B14*Inputs!B13*Inputs!B26)*(240000/Inputs!B7)*(0.35/Inputs!B21)-Inputs!B18
A13: 0.4 | B13: =Inputs!B8*Inputs!B9*0.4*Inputs!B23+(Inputs!B15*Inputs!B25+Inputs!B16*Inputs!B24+Inputs!B14*Inputs!B13*Inputs!B26)*(60000/Inputs!B7)*(0.4/Inputs!B21)-Inputs!B18 | C13: =Inputs!B8*Inputs!B9*0.4*Inputs!B23+(Inputs!B15*Inputs!B25+Inputs!B16*Inputs!B24+Inputs!B14*Inputs!B13*Inputs!B26)*(90000/Inputs!B7)*(0.4/Inputs!B21)-Inputs!B18 | D13: =Inputs!B8*Inputs!B9*0.4*Inputs!B23+(Inputs!B15*Inputs!B25+Inputs!B16*Inputs!B24+Inputs!B14*Inputs!B13*Inputs!B26)*(120000/Inputs!B7)*(0.4/Inputs!B21)-Inputs!B18 | E13: =Inputs!B8*Inputs!B9*0.4*Inputs!B23+(Inputs!B15*Inputs!B25+Inputs!B16*Inputs!B24+Inputs!B14*Inputs!B13*Inputs!B26)*(180000/Inputs!B7)*(0.4/Inputs!B21)-Inputs!B18 | F13: =Inputs!B8*Inputs!B9*0.4*Inputs!B23+(Inputs!B15*Inputs!B25+Inputs!B16*Inputs!B24+Inputs!B14*Inputs!B13*Inputs!B26)*(240000/Inputs!B7)*(0.4/Inputs!B21)-Inputs!B18
A15: Cells are formulas keyed off Inputs. Change Inputs to recompute.

Sheet Notes
A1: Evidence Room — AP Agent OS
A2: Notes & External Benchmarks
A3: Industry context only — not a guarantee of your results
A4: Agents that earn responsibility.
A6: Field | B6: Value
A7: Source | B7: Ardent Partners — State of ePayables (2025 survey averages)
A8: Avg cost per invoice | B8: $9.84
A9: Exception rate | B9: 18.4%
A10: Straight-through processing (STP) | B10: 35.4%
A11: Label | B11: EXTERNAL BENCHMARK — NOT A GUARANTEE
A12: How to use | B12: Locate your baseline relative to survey averages. Do not substitute these for measured KPIs or treat them as Evidence Room performance claims.
A13: Forbidden use | B13: Do not market 'guaranteed to reach $9.84'. Worksheets labeled ILLUSTRATIVE require your own inputs.
A14: Product | B14: Evidence Room provides methodologies and templates. Humans remain accountable for approvals, payments, and audit representations.

Sheet Disclaimer
A1: Evidence Room — AP Agent OS
A2: Disclaimer
A3: Read before relying on model outputs
A4: Agents that earn responsibility.
A6: Evidence Room products provide educational and operational templates for designing, governing, and measuring AI agents that assist Accounts Payable work.
A7: They are not legal, tax, audit, accounting, investment, or compliance advice.
A8: They are not a substitute for your ERP, AP automation platform, payment provider, or professional advisors.
A9: AI agents can be wrong. Humans remain accountable for approvals, postings, payments, supplier master changes, and representations to auditors.
A10: We do not guarantee any reduction in cost per invoice, cycle time, exception rate, fraud losses, compliance findings, or ROI.
A11: Industry benchmarks attributed to Ardent Partners (2025) — $9.84 avg cost/invoice, 18.4% exception rate, 35.4% STP — are third-party survey averages for context only. Cited only on Notes sheets.
A12: Any cell labeled ILLUSTRATIVE is sample data for structure demonstration — replace with your measured figures before decisions.
A13: Confidential — licensed for internal use by the purchasing organisation.
