Workbook

Sheet Inputs
A1: EVIDENCE ROOM · AP AGENT OS
A2: AP Agent business case — inputs
A3: Illustrative ranges. Not a forecast. No false precision.
A5: Input | B5: Value
A6: Monthly invoices | B6: 15000
A7: AP FTE | B7: 12
A8: Fully loaded cost per FTE (annual USD) | B8: 75000
A9: Manual-touch share | B9: 0.65
A10: Exception rate | B10: 0.22
A11: Average exception minutes | B11: 12
A12: Known duplicate rate (optional) | B12: 0.004
A13: Annual late-payment fees (optional) | B13: 0
A14: Annual early-pay discounts missed (optional) | B14: 0
A15: Annual AI/tool cost | B15: 24000
A16: Implementation cost (once) | B16: 40000
A17: Working hours per FTE-year | B17: 1720
... A23: Upside manual-touch reduction | B23: 0.15

Sheet Scenarios
A1: EVIDENCE ROOM · AP AGENT OS
A2: Scenarios — conservative / base / upside
A3: Labour economics only unless optional cash lines are completed.
A5: Line | B5: Conservative | C5: Base | D5: Upside
A6: Annual AP labour cost | B6: =Inputs!B7*Inputs!B8 | C6: =B6 | D6: =B6
A7: Annual invoices | B7: =Inputs!B6*12 | C7: =B7 | D7: =B7
A8: Implied labour cost / invoice | B8: =B6/B7 | C8: =B8 | D8: =B8
A9: Annual exceptions | B9: =B7*Inputs!B10 | C9: =B9 | D9: =B9
A10: Exception hours / year | B10: =B9*Inputs!B11/60 | C10: =B10 | D10: =B10
A11: Exception labour $ / year | B11: =B10*(Inputs!B8/Inputs!B17) | C11: =B11 | D11: =B11
A12: Exception labour reduction | B12: =Inputs!B18 | C12: =Inputs!B19 | D12: =Inputs!B20
A13: Manual-touch reduction | B13: =Inputs!B21 | C13: =Inputs!B22 | D13: =Inputs!B23
A14: Estimated exception $ released | B14: =B11*B12 | C14: =C11*C12 | D14: =D11*D12
A15: Estimated other-touch $ released | B15: =(B6-B11)*B13 | C15: =(C6-C11)*C13 | D15: =(D6-D11)*D13
A16: Optional cash lines (late + discount) | B16: =Inputs!B13+Inputs!B14 | C16: =B16 | D16: =B16
A17: Gross annual benefit (estimated) | B17: =B14+B15+B16 | C17: =C14+C15+C16 | D17: =D14+D15+D16
A18: Annual tool cost | B18: =Inputs!B15 | C18: =B18 | D18: =B18
A19: Net annual benefit before implementation | B19: =B17-B18 | C19: =C17-C18 | D19: =D17-D18
A20: Implementation cost | B20: =Inputs!B16 | C20: =B20 | D20: =B20
A21: Illustrative payback (months) | B21: =IF(B19<=0,"n/a",ROUND(B20/B19*12,0)) | C21: =IF(C19<=0,"n/a",ROUND(C20/C19*12,0)) | D21: =IF(D19<=0,"n/a",ROUND(D20/D19*12,0))
A22: Illustrative year-1 ROI | B22: =IF(B20=0,"n/a",(B19-B20)/B20) | C22: =IF(C20=0,"n/a",(C19-C20)/C20) | D22: =IF(D20=0,"n/a",(D19-D20)/D20)
A23: Hours released / year (estimated) | B23: =B10*B12+((B6-B11)/(Inputs!B8/Inputs!B17))*B13 | C23: =C10*C12+((C6-C11)/(Inputs!B8/Inputs!B17))*C13 | D23: =D10*D12+((D6-D11)/(Inputs!B8/Inputs!B17))*D13
A25: Sensitivity (base): volume ±20% and exception rate ±5pp change estimated exception hours, not fate.

Sheet Agent_economics
A1: EVIDENCE ROOM · AP AGENT OS
A2: Cost per correct outcome
A3: Track inference and reviewer time. Activity is not value.
A5: Agent | B5: Runs | C5: Correct | D5: Inference $ | E5: Reviewer hours | F5: Reviewer $ | G5: Cost / correct | H5: Notes
A6: 05 GR | B6: 200 | C6: 170 | D6: 12 | E6: 8 | F6: =E6*50 | G6: =IF(C6=0,"n/a",(D6+F6)/C6)
A7: 04 Triage | B7: 200 | C7: 170 | D7: 12 | E7: 8 | F7: =E7*50 | G7: =IF(C7=0,"n/a",(D7+F7)/C7)
A8: 02 Validation | B8: 200 | C8: 170 | D8: 12 | E8: 8 | F8: =E8*50 | G8: =IF(C8=0,"n/a",(D8+F8)/C8)
A9: 10 Anomaly | B9: 200 | C9: 170 | D9: 12 | E9: 8 | F9: =E9*50 | G9: =IF(C9=0,"n/a",(D9+F9)/C9)
A10: 12 Pay review | B10: 200 | C10: 170 | D10: 12 | E10: 8 | F10: =E10*50 | G10: =IF(C10=0,"n/a",(D10+F10)/C10)
