Workbook

Sheet Inputs
A1: EVIDENCE ROOM · AP AGENT OS
A2: AP Agent business case — inputs
A3: Change the yellow cells. Scenarios are ranges, not promises. External benchmarks are reference only.
A5: Driver | B5: Value | C5: Unit | D5: Notes
A6: Monthly invoice volume | B6: 15000 | C6: invoices | D6: All entities in scope
A7: AP FTE | B7: 18 | C7: FTE | D7: Shared services + in-country touching AP
A8: Fully loaded cost per FTE / year | B8: 85000 | C8: USD | D8: Salary, benefits, occupancy
A9: Manual-touch share | B9: 0.67 | C9: ratio | D9: 1 − current STP; if unknown use 0.67 (Ardent STP 32.6% is external)
A10: Exception rate | B10: 0.18 | C10: ratio | D10: Your 90-day rate; external range ~0.14–0.21
A11: Minutes per exception | B11: 22 | C11: minutes | D11: Time study or honest estimate
A12: Confirmed duplicate-payment rate | B12: 0.0004 | C12: ratio | D12: Your history; do not invent
A13: Average invoice value | B13: 2400 | C13: USD | D13: For duplicate $ exposure only
A14: Late-payment fees / year | B14: 18000 | C14: USD | D14: Documented only
A15: Early-pay discounts available / year | B15: 40000 | C15: USD | D15: Policy-eligible
A16: Discount capture today | B16: 0.35 | C16: ratio
A17: AP technology cost / year | B17: 120000 | C17: USD | D17: Current stack
A18: Incremental AI/tool cost / year | B18: 36000 | C18: USD | D18: Models, IDP increment, licences
A19: Implementation cost (once) | B19: 45000 | C19: USD | D19: Internal + this toolkit + integrator time
A20: Conservative exception-time reduction | B20: 0.12 | C20: ratio | D20: First bounded year
A21: Base exception-time reduction | B21: 0.22 | C21: ratio | D21: After two promoted agents
A22: Upside exception-time reduction | B22: 0.35 | C22: ratio | D22: Do not use as a pledge
A23: Discount capture lift (base) | B23: 0.15 | C23: ratio | D23: Points of available discounts
A24: Duplicate $ avoided (base, annual) | B24: 25000 | C24: USD | D24: Only if controls actually stop items
A26: Named cells map to the Model sheet. Yellow = input. Everything else is calculated.

Sheet Model
A1: EVIDENCE ROOM · AP AGENT OS
A2: Calculated case — conservative / base / upside
A3: FIN-06: do not report savings in a steer pack without Controller attestation.
A5: Output | B5: Conservative | C5: Base | D5: Upside | E5: Formula notes
A6: Annual invoice volume | B6: =Inputs!B6*12 | C6: =B6 | D6: =B6 | E6: Monthly × 12
A7: Annual fully loaded AP labour | B7: =Inputs!B7*Inputs!B8 | C7: =B7 | D7: =B7 | E7: FTE × cost
A8: Baseline processing cost (labour+tech) | B8: =B7+Inputs!B17 | C8: =B8 | D8: =B8 | E8: Excludes one-off impl
A9: Baseline exception hours | B9: =Inputs!B6*12*Inputs!B10*Inputs!B11/60 | C9: =B9 | D9: =B9 | E9: Vol × ex rate × minutes
A10: Exception labour $ (if all exceptions costed at FTE rate) | B10: =B9*(Inputs!B8/1800) | C10: =B10 | D10: =B10 | E10: 1800 hours / FTE year
A11: Hours released | B11: =B9*Inputs!B20 | C11: =B9*Inputs!B21 | D11: =B9*Inputs!B22 | E11: Reduction × exception hours
A12: Labour $ released (capacity, not automatic cash) | B12: =B11*(Inputs!B8/1800) | C12: =B12*(Inputs!B8/1800) | D12: =B13*(Inputs!B8/1800) | E12: Capacity unless roles change
A13: AI + incremental tool $ | B13: =Inputs!B18 | C13: =Inputs!B18 | D13: =Inputs!B18
A14: Net operating benefit year 1 (capacity – AI + discount lift + dup + late/2) | B14: =B12-B13+(Inputs!B15*Inputs!B23)+Inputs!B24*0.5+Inputs!B14*0.25 | C14: =C12-C13+(Inputs!B15*Inputs!B23)+Inputs!B24+Inputs!B14*0.5 | D14: =D12-D13+(Inputs!B15*Inputs!B23*1.2)+Inputs!B24*1.2+Inputs!B14*0.7 | E14: Discount and late effects are optional
A15: Implementation (once) | B15: =Inputs!B19 | C15: =Inputs!B19 | D15: =Inputs!B19
A16: Year-1 net after impl | B16: =B14-B15 | C16: =C14-C15 | D16: =D14-D15
A17: Simple payback (months) | B17: =IF(B14<=0,"n/m",B15/B14*12) | C17: =IF(C14<=0,"n/m",C15/C14*12) | D17: =IF(D14<=0,"n/m",D15/D14*12) | E17: Impl / annual benefit
A18: ROI on impl (year 1) | B18: =IF(B15=0,0,B16/B15) | C18: =IF(C15=0,0,C16/C15) | D18: =IF(D15=0,0,D16/D15) | E18: (Y1 net)/impl
A19: Cost per invoice baseline | B19: =(B8)/(B6) | C19: =C8/C6 | D19: =D8/D6 | E19: Labour+tech / volume
A20: Cost per invoice after (illustrative) | B20: =(B8+Inputs!B18-B12)/B6 | C20: =(C8+Inputs!B18-C12)/C6 | D20: =(D8+Inputs!B18-D12)/D6 | E20: Adds AI, subtracts capacity $
A22: Sensitivity: if implementation doubles (change Inputs!B19) payback moves linearly. If exception rate is unknown, do not publish a $ savings figure.

Sheet Benchmark_ref
A1: EVIDENCE ROOM · AP AGENT OS
A2: External reference — not your baseline
A3: See 09_RESEARCH/EVIDENCE_LEDGER.csv. Independence flags matter.
A5: Ledger | B5: Claim | C5: Figure | D5: Source
A6: AP-001 | B6: Avg cost / invoice (Ardent 2024) | C6: 9.4 | D6: Ardent State of ePayables 2024
A7: AP-009 | B7: Best-in-class cost / invoice | C7: 2.78 | D7: Ardent 2024
A8: AP-010 | B8: All-other cost / invoice | C8: 12.88 | D8: Ardent 2024
A9: AP-003 | B9: Exception rate (2024 SoE) | C9: 0.14 | D9: Ardent 2024
A10: AP-007 | B10: Exception rate (Metrics 2024) | C10: 0.207 | D10: Ardent / Basware dist.
A11: AP-016 | B11: Exception rate (2026 commentary) | C11: 0.184 | D11: Ardent Payables Place
A12: AP-004 | B12: STP (2024) | C12: 0.326 | D12: Ardent 2024
A13: AP-023 | B13: Finance AI with clear ROI | C13: 0.21 | D13: Deloitte 2026

Sheet Disclaimer
A1: Illustrative model. Not a guarantee of savings, ROI, or control effectiveness. Not legal, tax, or audit advice. Capacity is not cash unless a role or purchase is actually changed.
