Workbook

Sheet Inputs
A1: EVIDENCE ROOM · AP AGENT OS
A2: AP Agent business case — inputs
A3: Yellow = [BUYER]. Scenarios apply efficiency ranges only. Not a guarantee.
A5: ID | B5: Input | C5: Value | D5: Unit | E5: Notes
A6: I-01 | B6: Monthly invoice volume | C6: 8400 | D6: invoices | E6: ILLUSTRATIVE ACME default — overwrite
A7: I-02 | B7: AP operational headcount | C7: 14 | D7: FTE | E7: Processors, exception, query — not whole finance
A8: I-03 | B8: Fully loaded labour cost / FTE / year | C8: 85000 | D8: currency | E8: Overwrite with local loaded cost
A9: I-04 | B9: Manual-touch percentage | C9: 0.62 | D9: 0–1 | E9: Share with ≥1 human touch
A10: I-05 | B10: Exception rate | C10: 0.22 | D10: 0–1 | E10: Do not paste a blog rate without measuring
A11: I-06 | B11: Average resolution minutes | C11: 18 | D11: minutes | E11: Clocked, not hoped
A12: I-07 | B12: Known duplicate rate (detected) | C12: 0.004 | D12: 0–1 | E12: Detected, not 'fraud'
A13: I-08 | B13: Late-payment cost / year (known) | C13: 0 | D13: currency | E13: 0 if unknown — do not invent
A14: I-09 | B14: Early-pay discount missed / year | C14: 0 | D14: currency | E14: 0 if unknown
A15: I-10 | B15: Current processing cost / invoice (if known) | C15: 0 | D15: currency | E15: 0 = model will derive labour proxy
A16: I-11 | B16: AI / tool cost / year | C16: 36000 | D16: currency | E16: Licences + inference envelope
A17: I-12 | B17: Implementation cost (one-off) | C17: 45000 | D17: currency | E17: Internal time + external if any
A18: I-13 | B18: Working months / year | C18: 12 | D18: months | E18: Usually 12
A20: Scenario efficiency (share of current exception-touch hours that could be released — NOT a promise)
A21: Scenario | B21: Efficiency range (of exception hours) | C21: Hours-release haircut (realisation) | D21: Cash conversion of released hours | E21: Use
A22: Conservative | B22: 0.1 | C22: 0.5 | D22: 0 | E22: Capacity only; no cash until Controller signs
A23: Base | B23: 0.22 | C23: 0.65 | D23: 0.25 | E23: Partial backfill avoided
A24: Upside | B24: 0.35 | C24: 0.75 | D24: 0.4 | E24: Still not a guarantee
A26: Hackett 19 Nov 2025 software-adopter figures (60% touchless, 3.5× productivity at ≥30% touchless) are NOT inputs. Deloitte 8 Oct 2025: 63% AI deployed / 21% measurable ROI — treat ROI as something you must evidence, not copy.

Sheet Model
A1: EVIDENCE ROOM · AP AGENT OS
A2: Model
A3: Labour-proxy economics. Validated savings require a Controller signature — see Benefits tracker.
A5: Annual invoices | B5: =Inputs!C6*Inputs!C18
A6: Annual labour cost (AP ops) | B6: =Inputs!C7*Inputs!C8
A7: Derived labour $ / invoice | B7: =IF(B5=0,0,B6/B5)
A8: Exception invoices / year | B8: =B5*Inputs!C10
A9: Exception hours / year | B9: =B8*Inputs!C11/60
A10: Exception labour $ / year | B10: =IF(Inputs!C7=0,0,B9*(Inputs!C8/1800))
A11: Processing $ / invoice used | B11: =IF(Inputs!C15>0,Inputs!C15,B7)
A12: Baseline processing $ / year | B12: =B11*B5
A13: Late + missed discount (known only) | B13: =Inputs!C13+Inputs!C14
A14: Baseline total $ (labour proxy + known cash) | B14: =B6+B13
A15: AI + tool $ / year | B15: =Inputs!C16
A16: Implementation $ (one-off) | B16: =Inputs!C17
A18: Output | B18: Conservative | C18: Base | D18: Upside | E18: Unit | F18: Definition
A19: Hours released (after haircut) | B19: =Model!B9*Inputs!B22*Inputs!C22 | C19: =Model!B9*Inputs!B23*Inputs!C23 | D19: =Model!B9*Inputs!B24*Inputs!C24 | E19: hours | F19: Exception hours × efficiency × realisation haircut
A20: Capacity $ (not cash) | B20: =B19*(Inputs!C8/1800) | C20: =C19*(Inputs!C8/1800) | D20: =D19*(Inputs!C8/1800) | E20: currency | F20: Hours × loaded hourly (1800 h/FTE)
A21: Cash from released hours (conversion %) | B21: =B20*Inputs!D22 | C21: =C20*Inputs!D23 | D21: =D20*Inputs!D24 | E21: currency | F21: Only the converted slice is treated as cash-like
A22: Known cash levers used | B22: =Model!B13*0.15 | C22: =Model!B13*0.30 | D22: =Model!B13*0.45 | E22: currency | F22: Applied only if I-08/I-09 > 0. If zero, stays zero.
A23: Gross annual benefit (cash-like) | B23: =B21+B22 | C23: =C21+C22 | D23: =D21+D22 | E23: currency | F23: Converted hours + known cash levers
A24: Net annual (after AI run-cost) | B24: =B23-Model!B15 | C24: =C23-Model!B15 | D24: =D23-Model!B15 | E24: currency | F24: Does not amortise implementation
A25: Payback years (impl / net) | B25: =IF(B24<=0,"No payback",Model!B16/B24) | C25: =IF(C24<=0,"No payback",Model!B16/C24) | D25: =IF(D24<=0,"No payback",Model!B16/D24) | E25: years | F25: One-off / net annual. Blank if net ≤ 0
A26: ROI year-1 (net - impl) / impl | B26: =IF(Model!B16=0,"n/a",(B24-Model!B16)/Model!B16) | C26: =IF(Model!B16=0,"n/a",(C24-Model!B16)/Model!B16) | D26: =IF(Model!B16=0,"n/a",(D24-Model!B16)/Model!B16) | E26: ratio | F26: Negative is allowed and informative
A28: If Conservative net is negative, that is a finding — not a reason to invent a larger efficiency. Do not present Upside as the board case.

Sheet Sensitivity
A1: EVIDENCE ROOM · AP AGENT OS
A2: Sensitivity
A3: Exception rate vs efficiency (Base realisation and conversion). Illustrative grid.
A5: Exception rate → | B5: 0.1 | C5: 0.16 | D5: 0.22 | E5: 0.28 | F5: 0.34 | G5: Note
A6: Efficiency ↓ / Net annual $
A7: 0.1 | B7: =Inputs!$C$6*Inputs!$C$18*B$5*Inputs!$C$11/60*$A7*Inputs!$C$23*(Inputs!$C$8/1800)*Inputs!$D$23-Inputs!$C$16 | C7: =Inputs!$C$6*Inputs!$C$18*C$5*Inputs!$C$11/60*$A7*Inputs!$C$23*(Inputs!$C$8/1800)*Inputs!$D$23-Inputs!$C$16 | D7: =Inputs!$C$6*Inputs!$C$18*D$5*Inputs!$C$11/60*$A7*Inputs!$C$23*(Inputs!$C$8/1800)*Inputs!$D$23-Inputs!$C$16 | E7: =Inputs!$C$6*Inputs!$C$18*E$5*Inputs!$C$11/60*$A7*Inputs!$C$23*(Inputs!$C$8/1800)*Inputs!$D$23-Inputs!$C$16 | F7: =Inputs!$C$6*Inputs!$C$18*F$5*Inputs!$C$11/60*$A7*Inputs!$C$23*(Inputs!$C$8/1800)*Inputs!$D$23-Inputs!$C$16
A8: 0.16 | B8: =Inputs!$C$6*Inputs!$C$18*B$5*Inputs!$C$11/60*$A8*Inputs!$C$23*(Inputs!$C$8/1800)*Inputs!$D$23-Inputs!$C$16 | C8: =Inputs!$C$6*Inputs!$C$18*C$5*Inputs!$C$11/60*$A8*Inputs!$C$23*(Inputs!$C$8/1800)*Inputs!$D$23-Inputs!$C$16 | D8: =Inputs!$C$6*Inputs!$C$18*D$5*Inputs!$C$11/60*$A8*Inputs!$C$23*(Inputs!$C$8/1800)*Inputs!$D$23-Inputs!$C$16 | E8: =Inputs!$C$6*Inputs!$C$18*E$5*Inputs!$C$11/60*$A8*Inputs!$C$23*(Inputs!$C$8/1800)*Inputs!$D$23-Inputs!$C$16 | F8: =Inputs!$C$6*Inputs!$C$18*F$5*Inputs!$C$11/60*$A8*Inputs!$C$23*(Inputs!$C$8/1800)*Inputs!$D$23-Inputs!$C$16
A9: 0.22 | B9: =Inputs!$C$6*Inputs!$C$18*B$5*Inputs!$C$11/60*$A9*Inputs!$C$23*(Inputs!$C$8/1800)*Inputs!$D$23-Inputs!$C$16 | C9: =Inputs!$C$6*Inputs!$C$18*C$5*Inputs!$C$11/60*$A9*Inputs!$C$23*(Inputs!$C$8/1800)*Inputs!$D$23-Inputs!$C$16 | D9: =Inputs!$C$6*Inputs!$C$18*D$5*Inputs!$C$11/60*$A9*Inputs!$C$23*(Inputs!$C$8/1800)*Inputs!$D$23-Inputs!$C$16 | E9: =Inputs!$C$6*Inputs!$C$18*E$5*Inputs!$C$11/60*$A9*Inputs!$C$23*(Inputs!$C$8/1800)*Inputs!$D$23-Inputs!$C$16 | F9: =Inputs!$C$6*Inputs!$C$18*F$5*Inputs!$C$11/60*$A9*Inputs!$C$23*(Inputs!$C$8/1800)*Inputs!$D$23-Inputs!$C$16
A10: 0.28 | B10: =Inputs!$C$6*Inputs!$C$18*B$5*Inputs!$C$11/60*$A10*Inputs!$C$23*(Inputs!$C$8/1800)*Inputs!$D$23-Inputs!$C$16 | C10: =Inputs!$C$6*Inputs!$C$18*C$5*Inputs!$C$11/60*$A10*Inputs!$C$23*(Inputs!$C$8/1800)*Inputs!$D$23-Inputs!$C$16 | D10: =Inputs!$C$6*Inputs!$C$18*D$5*Inputs!$C$11/60*$A10*Inputs!$C$23*(Inputs!$C$8/1800)*Inputs!$D$23-Inputs!$C$16 | E10: =Inputs!$C$6*Inputs!$C$18*E$5*Inputs!$C$11/60*$A10*Inputs!$C$23*(Inputs!$C$8/1800)*Inputs!$D$23-Inputs!$C$16 | F10: =Inputs!$C$6*Inputs!$C$18*F$5*Inputs!$C$11/60*$A10*Inputs!$C$23*(Inputs!$C$8/1800)*Inputs!$D$23-Inputs!$C$16
A11: 0.35 | B11: =Inputs!$C$6*Inputs!$C$18*B$5*Inputs!$C$11/60*$A11*Inputs!$C$23*(Inputs!$C$8/1800)*Inputs!$D$23-Inputs!$C$16 | C11: =Inputs!$C$6*Inputs!$C$18*C$5*Inputs!$C$11/60*$A11*Inputs!$C$23*(Inputs!$C$8/1800)*Inputs!$D$23-Inputs!$C$16 | D11: =Inputs!$C$6*Inputs!$C$18*D$5*Inputs!$C$11/60*$A11*Inputs!$C$23*(Inputs!$C$8/1800)*Inputs!$D$23-Inputs!$C$16 | E11: =Inputs!$C$6*Inputs!$C$18*E$5*Inputs!$C$11/60*$A11*Inputs!$C$23*(Inputs!$C$8/1800)*Inputs!$D$23-Inputs!$C$16 | F11: =Inputs!$C$6*Inputs!$C$18*F$5*Inputs!$C$11/60*$A11*Inputs!$C$23*(Inputs!$C$8/1800)*Inputs!$D$23-Inputs!$C$16
A13: Grid uses Base haircut and Base cash conversion. It is a thinking tool, not a forecast.

Sheet Disclaimers
A1: EVIDENCE ROOM · AP AGENT OS
A2: Disclaimers
A3: This workbook does not certify savings, ROI, fraud prevention, or compliance.
A5: Evidence Room provides a model. The buyer provides the facts.
A6: Released hours are not cash until a Controller decides not to backfill or to reduce overtime / contractor.
A7: Agent 10 findings are not a fraud opinion.
A8: Do not cite Hackett or Deloitte numbers as your results.
A9: Counsel and tax advisers are not replaced by this file.
