Workbook

Sheet START
A1: EVIDENCE ROOM · AP AGENT OS
A2: AP AI Readiness Diagnostic — Scorecard
A3: 36 questions · 0–4 rubric · unweighted · 30–40 minutes. Proof before permission.
A5: How to score
A6: 0 = Absent / unknown. 1 = Informal / hero-dependent. 2 = Partial / uneven. 3 = Documented and mostly used. 4 = Operated, sampled, and evidenced.
A7: Do not score what you hope is true. Score what you can show on Monday.
A8: Unweighted: 36 × 4 = 144. Domain subtotals (0–24) matter more than the headline.
A9: Hard brakes: if CA-02 (bank-change vs payment SoD) is 0–1, do not interpret a high AR score as permission to execute.
A10: No industry target is pre-filled. Deloitte / APQC / Hackett figures are market context in the PDF, not your score.
A11: Yellow cells on Answers are [BUYER] inputs. Do not overwrite formulas on Results.
A13: Organisation (optional) | B13: [BUYER legal name]
A14: Scored by | B14: [BUYER name / role]
A15: Date | B15: [YYYY-MM-DD]
A16: Entities in scope | B16: [BUYER]

Sheet Answers
A1: EVIDENCE ROOM · AP AGENT OS
A2: Answers
A3: Enter Score 0–4 only. Rubric text is a reminder — do not score the reminder.
A5: ID | B5: Domain | C5: Question | D5: Score 0–4 | E5: Evidence pointer | F5: Notes
A6: PI-01 | B6: Process integrity | C6: Invoice channels are documented (email, portal, EDI, scan) with an owner per channel.
A7: PI-02 | B7: Process integrity | C7: PO vs non-PO policy is written and used, not tribal.
A8: PI-03 | B8: Process integrity | C8: Matching rules (2-way / 3-way / tolerances) are published per category.
A9: PI-04 | B9: Process integrity | C9: Exception reason codes exist and are used on the queue.
A10: PI-05 | B10: Process integrity | C10: Aged exceptions have a named owner and a clock.
A11: PI-06 | B11: Process integrity | C11: Month-end AP completeness (GR/IR, unprocessed, blocked) has a checklist.
A12: DS-01 | B12: Data & systems | C12: Invoice image/PDF is retrievable from the case, not only a posted header.
A13: DS-02 | B13: Data & systems | C13: Vendor master quality is measured (duplicates, inactive, bank-change trail).
A14: DS-03 | B14: Data & systems | C14: PO, GR, invoice, and payment keys can be joined without a hero spreadsheet.
A15: DS-04 | B15: Data & systems | C15: Legal entity / company code is reliable on the invoice packet.
A16: DS-05 | B16: Data & systems | C16: Tax fields are captured and reconcilable to policy, not free text.
A17: DS-06 | B17: Data & systems | C17: Interface failures are visible (not silent drops).
... A41: AR-06 | B41: Agent readiness | C41: Leadership will accept L0 evidence before asking for L3.
A43: Validation: scores outside 0–4 will flag on Results. Blank is treated as unanswered, not zero.

Sheet Results
A1: EVIDENCE ROOM · AP AGENT OS
A2: Results
A3: Formulas only. Do not type over this sheet.
A5: Domain | B5: Answered | C5: Sum | D5: Max possible | E5: Domain % | F5: Maturity hint
A6: Process integrity | B6: =COUNT(Answers!D6:D11) | C6: =SUM(Answers!D6:D11) | D6: =B6*4 | E6: =IF(D6=0,"—",C6/D6) | F6: =IF(B6<6,"Incomplete",IF(E6<0.25,"1 Unprepared",IF(E6<0.45,"2 Experimental",IF(E6<0.65,"3 Governed pilot",IF(E6<0.85,"4 Earned scale","5 Institutional")))))
A7: Data & systems | B7: =COUNT(Answers!D12:D17) | C7: =SUM(Answers!D12:D17) | D7: =B7*4 | E7: =IF(D7=0,"—",C7/D7) | F7: =IF(B7<6,"Incomplete",IF(E7<0.25,"1 Unprepared",IF(E7<0.45,"2 Experimental",IF(E7<0.65,"3 Governed pilot",IF(E7<0.85,"4 Earned scale","5 Institutional")))))
A8: Controls & audit | B8: =COUNT(Answers!D18:D23) | C8: =SUM(Answers!D18:D23) | D8: =B8*4 | E8: =IF(D8=0,"—",C8/D8) | F8: =IF(B8<6,"Incomplete",IF(E8<0.25,"1 Unprepared",IF(E8<0.45,"2 Experimental",IF(E8<0.65,"3 Governed pilot",IF(E8<0.85,"4 Earned scale","5 Institutional")))))
A9: Exception economics | B9: =COUNT(Answers!D24:D29) | C9: =SUM(Answers!D24:D29) | D9: =B9*4 | E9: =IF(D9=0,"—",C9/D9) | F9: =IF(B9<6,"Incomplete",IF(E9<0.25,"1 Unprepared",IF(E9<0.45,"2 Experimental",IF(E9<0.65,"3 Governed pilot",IF(E9<0.85,"4 Earned scale","5 Institutional")))))
A10: Talent & operating model | B10: =COUNT(Answers!D30:D35) | C10: =SUM(Answers!D30:D35) | D10: =B10*4 | E10: =IF(D10=0,"—",C10/D10) | F10: =IF(B10<6,"Incomplete",IF(E10<0.25,"1 Unprepared",IF(E10<0.45,"2 Experimental",IF(E10<0.65,"3 Governed pilot",IF(E10<0.85,"4 Earned scale","5 Institutional")))))
A11: Agent readiness | B11: =COUNT(Answers!D36:D41) | C11: =SUM(Answers!D36:D41) | D11: =B11*4 | E11: =IF(D11=0,"—",C11/D11) | F11: =IF(B11<6,"Incomplete",IF(E11<0.25,"1 Unprepared",IF(E11<0.45,"2 Experimental",IF(E11<0.65,"3 Governed pilot",IF(E11<0.85,"4 Earned scale","5 Institutional")))))
A13: TOTAL | B13: =SUM(B6:B11) | C13: =SUM(C6:C11) | D13: =SUM(D6:D11) | E13: =IF(D13=0,"—",C13/D13) | F13: =IF(B13<36,"Incomplete — do not over-interpret",IF(E13<0.25,"1 Unprepared",IF(E13<0.45,"2 Experimental",IF(E13<0.65,"3 Governed pilot",IF(E13<0.85,"4 Earned scale","5 Institutional")))))
A15: Hard brake | B15: =IF(Answers!D18="","Unanswered CA-02",IF(Answers!D18<=1,"BRAKE — SoD too weak to interpret Agent readiness as execute-ready","OK — SoD not at 0–1"))
A17: Out-of-range scores | B17: =COUNTIFS(Answers!D6:D41,">4")+COUNTIFS(Answers!D6:D41,"<0")
A19: Maturity bands are interpretive aids, not a certification. A high score is not permission to pay autonomously.

Sheet Heatmap
A1: EVIDENCE ROOM · AP AGENT OS
A2: Opportunity heatmap
A3: Buyer-scored. Volume × pain × control risk × data readiness. Not a vendor ranking.
A5: Candidate (first-wave agent) | B5: Volume 1–5 | C5: Pain 1–5 | D5: Control risk 1–5 (higher = more sensitive) | E5: Data readiness 1–5 | F5: Priority index (vol×pain×data / risk)
A6: 01 Invoice Intake | F6: =IF(OR(B6="",C6="",D6="",E6=""),"",IF(D6=0,"", (B6*C6*E6)/D6))
A7: 02 Invoice Validation | F7: =IF(OR(B7="",C7="",D7="",E7=""),"",IF(D7=0,"", (B7*C7*E7)/D7))
A8: 03 Matching | F8: =IF(OR(B8="",C8="",D8="",E8=""),"",IF(D8=0,"", (B8*C8*E8)/D8))
A9: 04 Exception Triage | F9: =IF(OR(B9="",C9="",D9="",E9=""),"",IF(D9=0,"", (B9*C9*E9)/D9))
A10: 05 Goods Receipt | F10: =IF(OR(B10="",C10="",D10="",E10=""),"",IF(D10=0,"", (B10*C10*E10)/D10))
A11: 07 Approval | F11: =IF(OR(B11="",C11="",D11="",E11=""),"",IF(D11=0,"", (B11*C11*E11)/D11))
A12: 08 Supplier Resolution | F12: =IF(OR(B12="",C12="",D12="",E12=""),"",IF(D12=0,"", (B12*C12*E12)/D12))
A13: 09 Internal Follow-Up | F13: =IF(OR(B13="",C13="",D13="",E13=""),"",IF(D13=0,"", (B13*C13*E13)/D13))
A14: 10 Duplicate & Anomaly | F14: =IF(OR(B14="",C14="",D14="",E14=""),"",IF(D14=0,"", (B14*C14*E14)/D14))
A15: 16 Orchestrator | F15: =IF(OR(B15="",C15="",D15="",E15=""),"",IF(D15=0,"", (B15*C15*E15)/D15))
A17: Higher index = better first-slice candidate only if control risk is honestly scored. Do not game risk down to force Intake into execute.

Sheet Baseline_KPI
A1: EVIDENCE ROOM · AP AGENT OS
A2: Baseline KPI worksheet
A3: Buyer fills actuals. No fake industry targets.
A5: KPI | B5: Your figure | C5: Period | D5: Source system / extract | E5: Owner
A6: Monthly invoice volume
A7: Exception rate %
A8: Straight-through / first-pass yield % (define locally)
A9: Median days invoice receipt → post
A10: Aged exceptions > 15 days (count)
A11: Duplicate invoices detected pre-payment (count)
A12: Cost per invoice (fully loaded proxy)
A13: AP FTE (or hours) on exceptions
A14: On-time payment %
A15: Missing GR open items (count)

Sheet Case_starter
A1: EVIDENCE ROOM · AP AGENT OS
A2: Business-case starter (inputs only)
A3: No promised savings. Feeds the Professional model later.
A5: Input | B5: Value | C5: Unit | D5: Notes
A6: Monthly invoices | C6: count | D6: [BUYER]
A7: AP operational FTE | C7: FTE | D7: Processors + exception + query
A8: Fully loaded cost per FTE / year | C8: currency | D8: Use local loaded rate
A9: Manual-touch share | C9: 0–1 | D9: Invoices with ≥1 human touch
A10: Exception rate | C10: 0–1 | D10: From your queue, not a blog
A11: Avg resolution minutes | C11: minutes | D11: Top families if overall unknown
A12: AI / tool cost / month (expected) | C12: currency | D12: Leave blank if unknown
A13: Implementation hours (expected) | C13: hours | D13: Internal + external
A15: Conservative / Base / Upside efficiency ranges belong in the Professional ROI workbook. This sheet only captures inputs.
