Workbook

Sheet COVER
A1: Outputs are arithmetic on your inputs. They are not a forecast and not a promise of savings, payback, or ROI. Duplicate-suspect lines do not create savings. Leave unknown inputs blank; do not replace them with industry averages.
A3: EVIDENCE ROOM — AP AGENT OS
A4: Business-case workbook · Professional
A6: Organisation | B6: Northline Industrials (replace)
A7: Owner
A8: Date | B8: 2026-09-20
A9: Envelope | B9: Narrow / Central / Inclusive — state which you are using
A11: Do not copy Ardent or McKinsey figures into INPUTS. RESEARCH is locked text only.

Sheet INPUTS
A1: Yellow = required for baseline. Blue = optional. Orange = efficiency cases (I13). Blank means unknown — do not fill with industry averages.
A3: ID | B3: Name | C3: Named range | D3: Value | E3: Unit | F3: Notes
A4: I1 | B4: Annual invoice volume | C4: vol_invoices | D4: 180000 | E4: invoices | F4: Northline illustration: 15,000 / month
A5: I2 | B5: AP FTE on path | C5: fte_path | D5: 14 | E5: FTE | F5: Path labour only
A6: I3 | B6: Fully loaded cost / FTE | C6: loaded_cost_fte | D6: 85000 | E6: USD / year
A7: I4 | B7: Hours per FTE | C7: hours_per_fte | D7: 1800 | E7: hours | F7: Must stay visible
A8: I5 | B8: Manual-touch share | C8: manual_touch_pct | D8: 0.55 | E8: 0-1
A9: I6 | B9: Minutes per manual touch | C9: minutes_per_touch | D9: 8 | E9: minutes | F9: Required for T
A10: I7 | B10: Exception rate | C10: exception_rate | D10: 0.22 | E10: 0-1 | F10: Your rate, not a benchmark target
A11: I8 | B11: Minutes per exception | C11: minutes_per_exception | D11: 25 | E11: minutes
A12: I9 | B12: Mechanical share of exceptions | C12: mechanical_share_of_exc | D12: 0 | E12: 0-1 | F12: Default 0 until justified
A13: I10 | B13: Duplicate-suspect rate | C13: dup_suspect_rate | D13: 0.01 | E13: 0-1 | F13: DISPLAY ONLY — not used in savings
A14: I11a | B14: Late-pay cost (known) | C14: late_pay_cost | E14: USD / year | F14: Blank = 0 credit
A15: I11b | B15: Early-pay captured (known) | C15: early_pay_captured | E15: USD / year | F15: Blank = 0 credit
A16: I12a | B16: Tool / model run cost | C16: tool_cost | D16: 40000 | E16: USD / year
A17: I12b | B17: Implementation cost | C17: impl_cost | D17: 75000 | E17: USD
A18: I13c | B18: Efficiency Conservative | C18: eff_c | D18: 0.08 | E18: 0-1 | F18: Hours released share
A19: I13b | B19: Efficiency Base | C19: eff_b | D19: 0.15 | E19: 0-1
A20: I13u | B20: Efficiency Upside | C20: eff_u | D20: 0.25 | E20: 0-1
A21: I14 | B21: Amortisation years | C21: amort_years | D21: 3 | E21: years | F21: For ROI display only
A24: Use CASES sheet. Do not paste vendor $2.78 / $12.88 into D5.

Sheet DERIVED
A1: Derived. If INPUTS!D4 is 0 or blank, CPI is NA. If exception labour > people cost, flag INPUT_INCONSISTENT.
A3: Metric | B3: Formula result
A4: Hourly rate | B4: =IF(INPUTS!D7=0,NA(),INPUTS!D6/INPUTS!D7)
A5: D1 People cost | B5: =INPUTS!D5*INPUTS!D6
A6: D2 Exceptions | B6: =INPUTS!D4*INPUTS!D10
A7: D3 Exception hours | B7: =B6*INPUTS!D11/60
A8: D4 Exception labour | B8: =B7*B4
A9: T minutes | B9: =INPUTS!D4*INPUTS!D8*INPUTS!D9
A10: T hours | B10: =B9/60
A11: D5 CPI (Narrow: people/volume) | B11: =IF(OR(INPUTS!D4="",INPUTS!D4=0),NA(),B5/INPUTS!D4)
A12: D6 Run cost | B12: =INPUTS!D16
A13: D7 Year-1 cash out | B13: =INPUTS!D16+INPUTS!D17
A14: Consistency | B14: =IF(B8>B5,"INPUT_INCONSISTENT","OK")
A15: Dup-suspect count (display only) | B15: =INPUTS!D4*INPUTS!D13
A16: Dup-suspect savings (forced) | B16: 0
A19: Hours released are not validated financial savings until Finance attests a method.

Sheet CASES
A1: Conservative / Base / Upside. Duplicate-suspect savings remain 0 in every case.
A3: Line | B3: Conservative | C3: Base | D3: Upside
A4: Efficiency applied | B4: =INPUTS!D18 | C4: =INPUTS!D19 | D4: =INPUTS!D20
A5: Hours released (estimated) | B5: =DERIVED!B10*B4 | C5: =DERIVED!B10*C4 | D5: =DERIVED!B10*D4
A6: Labour capacity value (estimated) | B6: =B5*DERIVED!B4 | C6: =C5*DERIVED!B4 | D6: =D5*DERIVED!B4
A7: Late-pay / discount change (only if you entered it) | B7: =IF(INPUTS!D14="",0,0) | C7: =IF(INPUTS!D15="",0,0) | D7: 0
A8: Duplicate-suspect savings | B8: 0 | C8: 0 | D8: 0
A9: Run + impl (year 1) | B9: =DERIVED!B13 | C9: =DERIVED!B13 | D9: =DERIVED!B13
A10: Net year-1 (estimated capacity minus cash out) | B10: =B6+B7+B8-B9 | C10: =C6+C7+C8-C9 | D10: =D6+D7+D8-D9
A11: Simple payback years (if net>0 after impl amortised) | B11: =IF((B6-DERIVED!B12)<=0,"n/a",INPUTS!D21) | C11: =IF((C6-DERIVED!B12)<=0,"n/a",INPUTS!D21) | D11: =IF((D6-DERIVED!B12)<=0,"n/a",INPUTS!D21)

Sheet SENSITIVITY
A1: One-way shocks on Base efficiency. Not a forecast.
A3: Shock | B3: Base hours released
A4: Volume -20% | B4: =CASES!C5*0.8
A5: Volume +20% | B5: =CASES!C5*1.2
A6: Efficiency = Conservative | B6: =CASES!B5
A7: Efficiency = Upside | B7: =CASES!D5
A8: Touch minutes +25% | B8: =CASES!C5*1.25

Sheet CPI
A1: Cost per invoice — Narrow envelope uses people cost / volume. Do not subtract vendor Best-in-Class $2.78.
A3: Narrow CPI | B3: =DERIVED!B11
A4: Exception labour / invoice | B4: =IF(INPUTS!D4=0,NA(),DERIVED!B8/INPUTS!D4)

Sheet RESEARCH
A1: Locked citations. Do not write formulas that consume these numbers as targets.
A3: Claim | B3: Value | C3: Independence | D3: Source
A4: Best-in-Class vs All Others cost / invoice (Ardent 2024 via Tipalti) | B4: $2.78 vs $12.88 | C4: vendor-citing-independent | D4: Ardent State of ePayables 2024; hop: tipalti.com AI invoice processing
A5: Best-in-Class vs All Others cycle time (Ardent 2024 via Tipalti) | B5: 3.1 vs 17.4 days | C5: vendor-citing-independent | D5: Same hop. Class split, not your before/after.
A6: Exception rates cited as 22% and 9% (Ardent 2025 via Tipalti) | B6: 22% / 9% | C6: vendor-citing-independent | D6: AP Metrics that Matter 2025 hop. Not a measured automation delta for you.
A7: CFOs using gen AI for >5 use cases (McKinsey Nov 2025) | B7: 44% of 102 (from 7%) | C7: independent | D7: How finance teams are putting AI to work today
A8: Regular AI use ≥1 function (McKinsey State of AI 2025) | B8: 88% (from 78%) | C8: independent | D8: Survey 25 Jun–29 Jul 2025, n=1,993
A9: Not yet scaling AI across the enterprise | B9: nearly two-thirds | C9: independent | D9: Same
A10: At least experimenting with AI agents | B10: 62% | C10: independent | D10: Same
A11: Scaling an agentic system somewhere | B11: 23% | C11: independent | D11: Same
A12: Any EBIT impact attributed to AI | B12: 39% | C12: independent | D12: Same

Sheet AUDIT
A1: Who attested each material input.
A3: Input | B3: Source system / file | C3: Date | D3: Attested by
A4: Volume
A5: FTE
A6: Loaded cost
A7: Exception rate
A8: Tool cost
